method_lines/__init__.py
method_lines/drivers.py
method_lines/commands/__init__.py
method_lines/commands/all.py
method_lines/commands/buddies.py
method_lines/commands/clean.py
method_lines/commands/composition.py
method_lines/commands/grids.py
method_lines/commands/gsiril.py
method_lines/commands/lines.py
method_lines/commands/places.py
method_lines/commands/rows.py
method_lines/configs/__init__.py
method_lines/configs/bells.py
method_lines/configs/calls.py
method_lines/configs/composition.py
method_lines/configs/methods.py
method_lines/utils/__init__.py
method_lines/utils/shell.py
method_lines-0.1.2.data/scripts/execute.py
method_lines-0.1.2.dist-info/DESCRIPTION.rst
method_lines-0.1.2.dist-info/METADATA
method_lines-0.1.2.dist-info/RECORD
method_lines-0.1.2.dist-info/WHEEL
method_lines-0.1.2.dist-info/entry_points.txt
method_lines-0.1.2.dist-info/metadata.json
method_lines-0.1.2.dist-info/top_level.txt
