Metadata-Version: 2.0
Name: method-lines
Version: 0.1.2
Summary: Produces method lines and resources for peals in parts.
Home-page: https://github.com/simpleigh/
Author: Leigh Simpson
Author-email: code@simpleigh.com
License: GPL
Platform: UNKNOWN
Classifier: Development Status :: 3 - Alpha
Classifier: Environment :: Console
Classifier: Intended Audience :: End Users/Desktop
Classifier: License :: OSI Approved :: GNU General Public License v3 (GPLv3)
Classifier: Operating System :: POSIX :: Linux
Classifier: Programming Language :: Python :: 2
Classifier: Programming Language :: Python :: 2.6
Classifier: Programming Language :: Python :: 2.7
Classifier: Programming Language :: Python :: 3
Classifier: Programming Language :: Python :: 3.3
Classifier: Programming Language :: Python :: 3.4
Classifier: Programming Language :: Python :: 3.5
Requires-Dist: XlsxWriter
Requires-Dist: ringing-lib (>=0.3)
Requires-Dist: six
